README.md
setup.cfg
setup.py
pygres/__init__.py
pygres/config.py
pygres/errors.py
pygres/model.py
pygres/pygres.py
pygres.egg-info/PKG-INFO
pygres.egg-info/SOURCES.txt
pygres.egg-info/dependency_links.txt
pygres.egg-info/requires.txt
pygres.egg-info/top_level.txt