Metadata-Version: 1.1
Name: pygres
Version: 1.4.0
Summary: Postgres simple connector
Home-page: https://github.com/rogamba/pygres
Author: Rodrigo Gamba
Author-email: gamba.lavin@gmail.com
License: UNKNOWN
Download-URL: https://github.com/rogamba/pygres/tarball/0.1
Keywords: postgres,psql,postgresql
Platform: UNKNOWN
